pgbackup/__init__.py
pgbackup/cli.py
pgbackup/pgdump.py
pgbackup/storage.py
pgbackup-1.0.1.dist-info/LICENSE
pgbackup-1.0.1.dist-info/METADATA
pgbackup-1.0.1.dist-info/WHEEL
pgbackup-1.0.1.dist-info/entry_points.txt
pgbackup-1.0.1.dist-info/top_level.txt
pgbackup-1.0.1.dist-info/RECORD
